README.rst
setup.py
djangothis/__init__.py
djangothis/app.py
djangothis/models.py
djangothis/path.py
djangothis/tests.py
djangothis.egg-info/PKG-INFO
djangothis.egg-info/SOURCES.txt
djangothis.egg-info/dependency_links.txt
djangothis.egg-info/entry_points.txt
djangothis.egg-info/not-zip-safe
djangothis.egg-info/requires.txt
djangothis.egg-info/top_level.txt
djangothis/management/__init__.py
djangothis/management/commands/__init__.py
djangothis/management/commands/gunicorn.py
djangothis/templatetags/__init__.py
djangothis/templatetags/raw.py