Metadata-Version: 1.0
Name: djangothis
Version: 0.9
Summary: Serve static files and django templates in current folder.
Home-page: http://amitu.com/djangothis/
Author: Amit Upadhyay
Author-email: upadhyay@gmail.com
License: BSD
Platform: UNKNOWN
